deepdoctection/__init__.py
deepdoctection/py.typed
deepdoctection/analyzer/__init__.py
deepdoctection/analyzer/config.py
deepdoctection/analyzer/dd.py
deepdoctection/analyzer/factory.py
deepdoctection/configs/__init__.py
deepdoctection/configs/conf_dd_one.yaml
deepdoctection/configs/conf_tesseract.yaml
deepdoctection/configs/profiles.jsonl
deepdoctection/eval/__init__.py
deepdoctection/eval/accmetric.py
deepdoctection/eval/base.py
deepdoctection/eval/cocometric.py
deepdoctection/eval/eval.py
deepdoctection/eval/registry.py
deepdoctection/eval/tedsmetric.py
deepdoctection/extern/__init__.py
deepdoctection/extern/base.py
deepdoctection/extern/d2detect.py
deepdoctection/extern/deskew.py
deepdoctection/extern/doctrocr.py
deepdoctection/extern/hfdetr.py
deepdoctection/extern/hflayoutlm.py
deepdoctection/extern/hflm.py
deepdoctection/extern/model.py
deepdoctection/extern/pdftext.py
deepdoctection/extern/tessocr.py
deepdoctection/extern/texocr.py
deepdoctection/pipe/__init__.py
deepdoctection/pipe/anngen.py
deepdoctection/pipe/base.py
deepdoctection/pipe/common.py
deepdoctection/pipe/concurrency.py
deepdoctection/pipe/doctectionpipe.py
deepdoctection/pipe/language.py
deepdoctection/pipe/layout.py
deepdoctection/pipe/lm.py
deepdoctection/pipe/order.py
deepdoctection/pipe/refine.py
deepdoctection/pipe/registry.py
deepdoctection/pipe/segment.py
deepdoctection/pipe/sub_layout.py
deepdoctection/pipe/text.py
deepdoctection/pipe/transform.py
deepdoctection/train/__init__.py
deepdoctection/train/d2_frcnn_train.py
deepdoctection/train/hf_detr_train.py
deepdoctection/train/hf_layoutlm_train.py
deepdoctection-1.0.6.dist-info/METADATA
deepdoctection-1.0.6.dist-info/WHEEL
deepdoctection-1.0.6.dist-info/top_level.txt
deepdoctection-1.0.6.dist-info/RECORD
