Metadata-Version: 2.4
Name: deepdoctection
Version: 1.0.6
Summary: Repository for Document AI - server/inference core package
Author: Dr. Janis Meyer
License: Apache License 2.0
Project-URL: Homepage, https://github.com/deepdoctection/deepdoctection
Project-URL: Documentation, https://deepdoctection.readthedocs.io
Project-URL: Repository, https://github.com/deepdoctection/deepdoctection
Classifier: Development Status :: 4 - Beta
Classifier: License :: OSI Approved :: Apache Software License
Classifier: Natural Language :: English
Classifier: Operating System :: POSIX :: Linux
Classifier: Programming Language :: Python :: 3.10
Classifier: Programming Language :: Python :: 3.11
Classifier: Programming Language :: Python :: 3.12
Classifier: Topic :: Scientific/Engineering :: Artificial Intelligence
Requires-Python: >=3.10
Requires-Dist: dd-core[full]>=1.0.1
Requires-Dist: huggingface_hub>=0.26.0
Provides-Extra: full
Requires-Dist: dd-datasets[full]>=1.0.1; extra == "full"
Requires-Dist: boto3==1.34.102; extra == "full"
Requires-Dist: pdfplumber>=0.11.0; extra == "full"
Requires-Dist: jdeskew>=0.2.2; extra == "full"
Requires-Dist: networkx>=2.7.1; extra == "full"
Requires-Dist: apted==1.0.3; extra == "full"
Requires-Dist: distance==0.1.3; extra == "full"
Requires-Dist: lxml>=4.9.1; extra == "full"
Requires-Dist: pycocotools>=2.0.2; extra == "full"
Requires-Dist: timm>=0.9.16; extra == "full"
Requires-Dist: transformers<5.0.0,>=4.48.0; extra == "full"
Requires-Dist: accelerate>=0.29.1; extra == "full"
Requires-Dist: python-doctr>=1.0.0; extra == "full"
Provides-Extra: types
Requires-Dist: dd_core[types]; extra == "types"
Requires-Dist: lxml-stubs>=0.5.1; extra == "types"
Provides-Extra: dev
Requires-Dist: black==25.11.0; extra == "dev"
Requires-Dist: isort==7.0.0; extra == "dev"
Requires-Dist: pylint==4.0.2; extra == "dev"
Requires-Dist: mypy==1.4.1; extra == "dev"
Requires-Dist: types-PyYAML>=6.0.12.12; extra == "dev"
Requires-Dist: types-termcolor>=1.1.3; extra == "dev"
Requires-Dist: types-tabulate>=0.9.0.3; extra == "dev"
Requires-Dist: types-tqdm>=4.66.0.5; extra == "dev"
Requires-Dist: types-Pillow>=10.2.0.20240406; extra == "dev"
Requires-Dist: types-urllib3>=1.26.25.14; extra == "dev"
Requires-Dist: lxml-stubs>=0.5.1; extra == "dev"
Provides-Extra: test
Requires-Dist: pytest==9.0.1; extra == "test"
Requires-Dist: pytest-cov; extra == "test"
Provides-Extra: docs
Requires-Dist: mkdocs-material==9.7.0; extra == "docs"
Requires-Dist: mkdocstrings-python==1.19.0; extra == "docs"
Requires-Dist: griffe==1.13; extra == "docs"
